{
  "ts": "2026-03-05T22:11:34.206596+00:00",
  "run_id": "04da7d01-87a8-4b89-b9c5-29fcb10b9987:worker:ab5c7fcc-3f75-49c4-ba4c-d4ddf917e8ea:job:31680af6-d756-4fba-96d5-19e50c809ba6",
  "job_id": "31680af6-d756-4fba-96d5-19e50c809ba6",
  "action": "forge.propose",
  "context": {
    "deadletter_count": 0,
    "open_incident_count": 0,
    "active_mission_count": 0
  },
  "proposals": [
    {
      "name": "Workspace Signal Scanner",
      "description": "Scan workspace journals and produce a daily signal summary.",
      "rationale": "No pressing friction detected; propose a general utility capability.",
      "tags": [
        "workspace",
        "signals"
      ],
      "risk_tier": "low",
      "source": "baseline"
    }
  ]
}