{
  "ts": "2026-03-05T22:40:15.976981+00:00",
  "run_id": "8608bb44-a24c-4dc5-8041-ea9ab7a30da8:job:cf1d847f-7c0a-4c9f-893a-77bf256368c3",
  "job_id": "cf1d847f-7c0a-4c9f-893a-77bf256368c3",
  "action": "forge.propose",
  "context": {
    "deadletter_count": 0,
    "open_incident_count": 0,
    "active_mission_count": 1
  },
  "proposals": [
    {
      "name": "Workspace Signal Scanner",
      "description": "Scan workspace journals and produce a daily signal summary.",
      "rationale": "No pressing friction detected; propose a general utility capability.",
      "tags": [
        "workspace",
        "signals"
      ],
      "risk_tier": "low",
      "source": "baseline"
    }
  ]
}