{
  "ts": "2026-03-05T22:24:41.799804+00:00",
  "run_id": "f63bbd85-ac43-4b5c-b367-4eeb782866f4:job:e748133f-c951-4adb-ae9f-a17d0aaa08c1",
  "job_id": "e748133f-c951-4adb-ae9f-a17d0aaa08c1",
  "action": "forge.propose",
  "context": {
    "deadletter_count": 1,
    "open_incident_count": 0,
    "active_mission_count": 1
  },
  "proposals": [
    {
      "name": "Deadletter Triager",
      "description": "Automatically classify and summarize deadletter mission jobs.",
      "rationale": "Detected 1 deadletter jobs.",
      "tags": [
        "ops",
        "queue",
        "reliability"
      ],
      "risk_tier": "medium",
      "source": "queue.deadletter"
    }
  ]
}